ibb/__init__.py
ibb/_frontend.py
ibb/_util.py
ibb/_version.py
ibb/labextension/build_log.json
ibb/labextension/package.json
ibb/labextension/static/lib_imagecanvas_js-lib_repeatbutton_js-lib_unlinkbox_js-css_ibb_css.178944da73ed7be8e029.js
ibb/labextension/static/lib_imagecanvas_js-lib_repeatbutton_js-lib_unlinkbox_js-css_ibb_css.178944da73ed7be8e029.js.map
ibb/labextension/static/lib_index_js.4f20e055d4465607ff24.js
ibb/labextension/static/lib_index_js.4f20e055d4465607ff24.js.map
ibb/labextension/static/lib_plugin_js.d831588b03af80768465.js
ibb/labextension/static/lib_plugin_js.d831588b03af80768465.js.map
ibb/labextension/static/remoteEntry.1a3cd47d4d7aedec3766.js
ibb/labextension/static/remoteEntry.1a3cd47d4d7aedec3766.js.map
ibb/labextension/static/style.js
ibb/nbextension/extension.js
ibb/nbextension/index.js
ibb/nbextension/index.js.LICENSE.txt
ibb/nbextension/index.js.map
ibb/widgets/__init__.py
ibb/widgets/_brambox_viewer.py
ibb/widgets/_cutout_viewer.py
ibb/widgets/_image_canvas.py
ibb/widgets/_image_controls.py
ibb/widgets/_image_viewer.py
ibb/widgets/_index_counter.py
ibb/widgets/_patch_controls.py
ibb/widgets/_patch_viewer.py
ibb/widgets/_repeat_button.py
ibb/widgets/_torch_viewer.py
ibb/widgets/_unlink_box.py
ibb/widgets/_viewer.py
ibb-3.0.1.data/data/share/jupyter/labextensions/ibb/build_log.json
ibb-3.0.1.data/data/share/jupyter/labextensions/ibb/package.json
ibb-3.0.1.data/data/share/jupyter/labextensions/ibb/static/lib_imagecanvas_js-lib_repeatbutton_js-lib_unlinkbox_js-css_ibb_css.178944da73ed7be8e029.js
ibb-3.0.1.data/data/share/jupyter/labextensions/ibb/static/lib_imagecanvas_js-lib_repeatbutton_js-lib_unlinkbox_js-css_ibb_css.178944da73ed7be8e029.js.map
ibb-3.0.1.data/data/share/jupyter/labextensions/ibb/static/lib_index_js.4f20e055d4465607ff24.js
ibb-3.0.1.data/data/share/jupyter/labextensions/ibb/static/lib_index_js.4f20e055d4465607ff24.js.map
ibb-3.0.1.data/data/share/jupyter/labextensions/ibb/static/lib_plugin_js.d831588b03af80768465.js
ibb-3.0.1.dist-info/METADATA
ibb-3.0.1.dist-info/WHEEL
ibb-3.0.1.dist-info/licenses/LICENSE.txt
ibb-3.0.1.dist-info/RECORD
