Metadata-Version: 2.1
Name: ibb
Version: 3.0.1
Summary: Jupyter Widget Library for Brambox
Project-URL: Homepage, https://github.com/0phoff/ibb
Author-email: 0phoff <0phoff@users.noreply.github.com>
License: Copyright (c) 2022 0phoff
License-File: LICENSE.txt
Keywords: IPython,Jupyter,Widgets
Classifier: Framework :: Jupyter
Classifier: Intended Audience :: Developers
Classifier: Intended Audience :: Science/Research
Classifier: License :: OSI Approved :: BSD License
Classifier: Programming Language :: Python
Classifier: Programming Language :: Python :: 3
Classifier: Programming Language :: Python :: 3.7
Classifier: Programming Language :: Python :: 3.8
Classifier: Programming Language :: Python :: 3.9
Classifier: Programming Language :: Python :: 3.10
Requires-Python: >=3.7
Requires-Dist: brambox>2.0.0
Requires-Dist: ipywidgets<9,>=8
Requires-Dist: pillow
Requires-Dist: traittypes
Provides-Extra: docs
Requires-Dist: jupyter-sphinx; extra == 'docs'
Requires-Dist: nbsphinx; extra == 'docs'
Requires-Dist: nbsphinx-link; extra == 'docs'
Requires-Dist: pypandoc; extra == 'docs'
Requires-Dist: recommonmark; extra == 'docs'
Requires-Dist: sphinx-rtd-theme; extra == 'docs'
Requires-Dist: sphinx>=1.5; extra == 'docs'
Provides-Extra: examples
Requires-Dist: brambox[segment]; extra == 'examples'
Requires-Dist: tables; extra == 'examples'
Requires-Dist: torch; extra == 'examples'
Requires-Dist: torchvision; extra == 'examples'
